anax/__init__.py
anax/anax.py
anax/storage.py
anax-1.1.dist-info/LICENSE
anax-1.1.dist-info/METADATA
anax-1.1.dist-info/WHEEL
anax-1.1.dist-info/top_level.txt
anax-1.1.dist-info/RECORD
