Metadata-Version: 2.1
Name: anax
Version: 1.1
Summary: An encrypted non-linear database based on Pandas
Home-page: https://github.com/abrahamrhoffman/anaxdb
Author: Abraham Hoffman
Author-email: abrahamrhoffman@gmail.com
License: UNKNOWN
Platform: UNKNOWN
Classifier: Programming Language :: Python :: 2
Classifier: License :: OSI Approved :: MIT License
Classifier: Operating System :: OS Independent
Requires-Dist: pandas (==1.0.3)
Requires-Dist: numpy (==1.18.2)
Requires-Dist: pyarrow (==0.16.0)
Requires-Dist: matplotlib (==3.2.1)
Requires-Dist: seaborn (==0.10.0)
Requires-Dist: pycryptodome (==3.9.7)
Requires-Dist: pathlib (==1.0.1)
Requires-Dist: minio (==5.0.8)
